{
  "categorias": [
    {
      "id": 1,
      "titulo": "RPG",
      "cor": "#73FBD3",
      "link_extra": {
        "text": "Best RPG Games of All Time",
        "url": "https://www.ign.com/lists/top-100-rpgs"
      }
    },
    {
      "id": 2,
      "titulo": "Action",
      "cor": "#44E5E7",
      "link_extra": {
        "text": "Top Action Games of All Time",
        "url": "https://www.videogamer.com/top-games/action-games-all-time"
      }
    },
    {
      "id": 3,
      "titulo": "Adventure",
      "cor": "#59D2FE",
      "link_extra": {
        "text": "29 Essential, Must-Play Adventure Games",
        "url": "https://www.ign.com/articles/2017/05/19/29-essential-must-play-adventure-games"
      }
    },
    {
      "id": 4,
      "titulo": "Survival Horror",
      "cor": "#4A8FE7",
      "link_extra": {
        "text": "Silent Hill PS5 Rumors Explained: Is It Really Happening?",
        "url": "https://screenrant.com/silent-hill-ps5-rumors-leaks-playstation-release-announcement/"
      }
    },
    {
      "id": 5,
      "titulo": "Simulation",
      "cor": "#5C7AFF",
      "link_extra": {
        "text": "5 Reasons Why The Sims is the Greatest Video Game of All Time",
        "url": "https://metro.co.uk/2018/02/09/5-reasons-why-the-sims-is-the-greatest-video-game-of-all-time-7296620/"
      }
    }
  ],
  "videos": [
    {
      "id": 1,
      "categoriaId": 1,
      "titulo": "FINAL FANTASY VII Remake - O Início de Gameplay, em Português PT-BR | FF7 no PS4 Pro",
      "url": "https://www.youtube.com/watch?v=Cpgh0p14DLI",
      "videoDescription": "Vídeo gameplay do jogo Final Fantasy VII Remake, game disponível para PlayStation 4 e que gravei no PS4."
    },
    {
      "id": 2,
      "categoriaId": 1,
      "titulo": "Let's Play Chrono Trigger Part 1 - Good morning, Crono!",
      "url": "https://www.youtube.com/watch?v=CTuJI4efINs&t=1110s",
      "videoDescription": "Vídeo gameplay do jogo Final Fantasy VII Remake, game disponível para PlayStation 4 e que gravei no PS4."
    },
    {
      "id": 3,
      "categoriaId": 1,
      "titulo": "【 Persona 5 】 Anime RPG Live Stream - Part 1",
      "url": "https://www.youtube.com/watch?v=6fp2kI0IBXc&list=PLhn2BMescPmOTKB7VtQC88WQzMjkAh8P5",
      "videoDescription": "Persona 5 (Japanese: ペルソナ5 Hepburn: Perusona Faibu) is a role-playing video game developed by Atlus."
    },
    {
      "id": 4,
      "categoriaId": 1,
      "titulo": "Let's Play Final Fantasy VI! (Blind Playthrough) Part 1",
      "url": "https://www.youtube.com/watch?v=W1jS1_7DkDQ",
      "videoDescription": "Welcome to my new Let's Play Final Fantasy series! This time we're taking on an all time classic in Final Fantasy VI!"
    },
    {
      "id": 5,
      "categoriaId": 1,
      "titulo": "THE WITCHER 3: Wild Hunt - O Início de Gameplay, Dublado e Legendado em Português PT-BR",
      "url": "https://www.youtube.com/watch?v=TwIB-OdXMCY",
      "videoDescription": "Vídeo gameplay do jogo The Witcher 3 Wild Hunt em 1080p 60fps. Game rodando no PC, dublado e legendado em Português PT-BR."
    },
    {
      "id": 6,
      "categoriaId": 2,
      "titulo": "Uncharted Drake's Fortune - Parte 1: El Dorado!!!",
      "url": "https://www.youtube.com/watch?v=8ac_3007O24",
      "videoDescription": "Drake's Fortune na versão Collection do Playstation 4, com gráficos renovados, em 1080p60fps e totalmente dublado em Português do Brasil."
    },
    {
      "id": 7,
      "categoriaId": 2,
      "titulo": "Red Dead Redemption - Parte 1: John Marston! [ Xbox One - Playthrough ]",
      "url": "https://www.youtube.com/watch?v=0pZX9Jtt70U&t=569s",
      "videoDescription": "Primeiro Episódio do Clássico ÉPICO Red Dead Redemption, agora disponível no Xbox One"
    },
    {
      "id": 8,
      "categoriaId": 2,
      "titulo": "Halo 4 Gameplay Walkthrough Part 1 - Campaign Mission 1 - Dawn (H4)",
      "url": "https://www.youtube.com/watch?v=iTR1VJoJZVQ",
      "videoDescription": "NEW Halo 4 Gameplay Walkthrough Part 1 includes the Prologue and Mission 1: Dawn of the Halo 4 Campaign for Xbox 360."
    },
    {
      "id": 9,
      "categoriaId": 2,
      "titulo": "GHOST OF TSUSHIMA Walkthrough Gameplay Part 1 - INTRO (PS4 PRO)",
      "url": "https://www.youtube.com/watch?v=FWPielprQ2k&list=PLs1-UdHIwbo5fR4J12PDlJf6lyXU2oMYC",
      "videoDescription": "Ghost of Tsushima Walkthrough Gameplay Part 1"
    },
    {
      "id": 10,
      "categoriaId": 2,
      "titulo": "Fallout 4 Walkthrough Gameplay Part 1 - The Apocalypse (PS4)",
      "url": "https://www.youtube.com/watch?v=r9WsqRhbdF4",
      "videoDescription": "NEW Fallout 4 Walkthrough Gameplay Part 1 includes a Review, Character Creation and Mission 1 of Main Story for PS4, Xbox One and PC."
    },
    {
      "id": 11,
      "categoriaId": 3,
      "titulo": "HORIZON ZERO DAWN - O Início de Gameplay, em Português! (PS4 Pro)",
      "url": "https://www.youtube.com/watch?v=Uv6OvwqEPGM",
      "videoDescription": "Vídeo gameplay do jogo Horizon Zero Dawn, em Português PT-BR no PS4 Pro. Game exclusivo de PS4."
    },
    {
      "id": 12,
      "categoriaId": 3,
      "titulo": "Life Is Strange™ Episode 1: Chrysalis | Full Walkthrough",
      "url": "https://www.youtube.com/watch?v=0pZX9Jtt70U&t=569s",
      "videoDescription": "Life Is Strange™ Episode 1: Chrysalis | Full Walkthrough"
    },
    {
      "id": 13,
      "categoriaId": 3,
      "titulo": "Mass Effect Andromeda - Parte 1: Um Novo Começo!!!",
      "url": "https://www.youtube.com/watch?v=Dsk9-SbsLA0",
      "videoDescription": "Começando Mass Effect Andromeda, novo game da franquia que se passa a mais de 600 anos após os acontecimentos do ME3"
    },
    {
      "id": 14,
      "categoriaId": 3,
      "titulo": "DRAGON AGE INQUISITION - Gameplay do Início, em Português!",
      "url": "https://www.youtube.com/watch?v=pZ8MV-SI-DY",
      "videoDescription": "Vídeo gameplay de Dragon Age Inquisition, jogo legendado em Português PT-BR."
    },
    {
      "id": 15,
      "categoriaId": 3,
      "titulo": "DETROIT BECOME HUMAN Walkthrough Gameplay Part 1 - INTRO (PS4 Pro)",
      "url": "https://www.youtube.com/watch?v=t3cLDDwLeJA",
      "videoDescription": "PS4 Detroit Become Human Gameplay Walkthrough Part 1 of the Detroit Become Human Story Campaign including a Review, Intro and Chapter 1"
    },
    {
      "id": 16,
      "categoriaId": 4,
      "titulo": "RESIDENT EVIL 2 REMAKE : LEON A #1 - O INÍCIO DE GAMEPLAY",
      "url": "https://www.youtube.com/watch?v=YRpk5MPPl-U",
      "videoDescription": "Vídeo com o início de gameplay de Resident Evil 2 Remake legendado em Português."
    },
    {
      "id": 17,
      "categoriaId": 4,
      "titulo": "RESIDENT EVIL 2 REMAKE : LEON A #1 - O INÍCIO DE GAMEPLAY",
      "url": "https://www.youtube.com/watch?v=YRpk5MPPl-U",
      "videoDescription": "Vídeo com o início de gameplay de Resident Evil 2 Remake legendado em Português."
    },
    {
      "id": 18,
      "categoriaId": 4,
      "titulo": "Let's Watch - PT",
      "url": "https://www.youtube.com/watch?v=fF6IVUum7wI",
      "videoDescription": "Geoff, Jack, and Lindsay brave the horrors of PT while the rest of AH watches in delight."
    },
    {
      "id": 19,
      "categoriaId": 4,
      "titulo": "RESIDENT EVIL 3 REMAKE - O INÍCIO DE GAMEPLAY em Português",
      "url": "https://www.youtube.com/watch?v=4JRHKN02Ttk",
      "videoDescription": "Vídeo com a nossa tão esperada Gameplay do Início de Resident Evil 3 Remake Legendado em Português."
    },
    {
      "id": 20,
      "categoriaId": 4,
      "titulo": "LET YOUR STORY BEGIN | Until Dawn - Part 1",
      "url": "https://www.youtube.com/watch?v=aHmW4VBoSis",
      "videoDescription": "Until Dawn breaks open a branching horror story. Don't be fooled by the campy (and slightly cliche) setting."
    },
    {
      "id": 21,
      "categoriaId": 5,
      "titulo": "Stardew Valley #01 'Cansei da vida moderna' - Gameplay Fazenda estilo Harvest Moon ",
      "url": "https://www.youtube.com/watch?v=ALZg5XeOENQ",
      "videoDescription": "Acompanhe a gameplay traduzida e narrada em ptbr de Stardew Valley."
    },
    {
      "id": 22,
      "categoriaId": 5,
      "titulo": "Single Girl Tries The 100 Baby Challenge Season 1 Marathon | Sims 4",
      "url": "https://www.youtube.com/watch?v=3KFNMMeu9Ug",
      "videoDescription": "Single Girl Tries The 100 Baby Challenge Season 1 Marathon | Sims 4"
    },
    {
      "id": 23,
      "categoriaId": 5,
      "titulo": "Joguei THE SIMS 2 Depois de 10 Anos",
      "url": "https://www.youtube.com/watch?v=kk9tE4qTjWc",
      "videoDescription": "A última vez que joguei o The Sims 2 foi em 2009, então aproveitei o tédio da quarentena para jogar um dos meus jogos favoritos que eu nem lembrava como era."
    },
    {
      "id": 24,
      "categoriaId": 5,
      "titulo": "AMOR DOCE EM 2020",
      "url": "https://www.youtube.com/watch?v=PFCSNEfk0L4",
      "videoDescription": "AMOR DOCE EM 2020"
    },
    {
      "id": 25,
      "categoriaId": 5,
      "titulo": "HOW TO BE DADDY | Dream Daddy - Part 1",
      "url": "https://www.youtube.com/watch?v=9EcO-nOu8QE",
      "videoDescription": "Welcome to Dream Daddy! This amazing game from amazing people is all about dating some amazing dads!"
    }
  ]
}